README.md
setup.py
CNMCClient.egg-info/PKG-INFO
CNMCClient.egg-info/SOURCES.txt
CNMCClient.egg-info/dependency_links.txt
CNMCClient.egg-info/requires.txt
CNMCClient.egg-info/top_level.txt
cnmc_client/__init__.py
cnmc_client/client.py
cnmc_client/cnmc.py
cnmc_client/models.py