Metadata-Version: 1.1
Name: CNMCClient
Version: 0.4.1
Summary: Python client desired to interact with the CNMC API
Home-page: https://www.gisce.net
Author: GISCE-TI, S.L.
Author-email: devel@gisce.net
License: General Public Licence 3
Platform: UNKNOWN
Classifier: Programming Language :: Python
Classifier: Programming Language :: Python :: 2.7
Classifier: Programming Language :: Python :: 3
Classifier: Programming Language :: Python :: 3.6
Provides: cnmc_client
